ddrlibnx.py
genie_parsers_nx.py
ddr_pythonnx-0.1.52.dist-info/METADATA
ddr_pythonnx-0.1.52.dist-info/WHEEL
ddr_pythonnx-0.1.52.dist-info/top_level.txt
ddr_pythonnx-0.1.52.dist-info/RECORD
