Metadata-Version: 2.1
Name: ddr-pythonnx
Version: 0.1.52
Summary: Distributed Device Reasoning (DDR) NX-OS runtime
Home-page: https://wwwin-github.cisco.com/petervh/ddr-pythonnx
Author: Peter Van Horne
Author-email: petervh@cisco.com
License: UNKNOWN
Platform: UNKNOWN
Classifier: Programming Language :: Python :: 3
Classifier: License :: OSI Approved :: MIT License
Classifier: Operating System :: OS Independent
Requires-Python: >=3.6
